RMextract.libs/libgfortran-040039e1.so.5.0.0
RMextract.libs/libquadmath-96973f99.so.0.0.0
RMextract-0.5.1.dist-info/LICENSE
RMextract-0.5.1.dist-info/WHEEL
RMextract-0.5.1.dist-info/top_level.txt
RMextract-0.5.1.dist-info/entry_points.txt
RMextract-0.5.1.dist-info/RECORD
RMextract-0.5.1.dist-info/METADATA
RMextract/getTEC.py
RMextract/__init__.py
RMextract/logging.py
RMextract/getIONEX.py
RMextract/formatters.py
RMextract/PosTools.py
RMextract/getRM.py
RMextract/pyiriplas/ccir15.asc
RMextract/pyiriplas/dgrf1955.dat
RMextract/pyiriplas/kp1956
RMextract/pyiriplas/__init__.py
RMextract/pyiriplas/kp1955
RMextract/pyiriplas/ssn1_12.dat
RMextract/pyiriplas/kp1960
RMextract/pyiriplas/kp2015
RMextract/pyiriplas/kp1996
RMextract/pyiriplas/lyma_12.dat
RMextract/pyiriplas/kp1964
RMextract/pyiriplas/kp1987
RMextract/pyiriplas/kp1982
RMextract/pyiriplas/kp1981
RMextract/pyiriplas/ccir22.asc
RMextract/pyiriplas/kp1993
RMextract/pyiriplas/kp2000
RMextract/pyiriplas/kp2011
RMextract/pyiriplas/kp2018
RMextract/pyiriplas/igrf2015s.dat
RMextract/pyiriplas/kp2005
RMextract/pyiriplas/ccir12.asc
RMextract/pyiriplas/igin_12.dat
RMextract/pyiriplas/kp1973
RMextract/pyiriplas/kp1988
RMextract/pyiriplas/kp1972
RMextract/pyiriplas/dgrf1975.dat
RMextract/pyiriplas/ccir11.asc
RMextract/pyiriplas/kp1986
RMextract/pyiriplas/ig_rz.dat
RMextract/pyiriplas/ccir16.asc
RMextract/pyiriplas/kp1983
RMextract/pyiriplas/kp1948
RMextract/pyiriplas/dgrf1995.dat
RMextract/pyiriplas/kp1997
RMextract/pyiriplas/dgrf1950.dat
RMextract/pyiriplas/igrf2015.dat
RMextract/pyiriplas/kp1978
RMextract/pyiriplas/kp1947
RMextract/pyiriplas/kp1977
RMextract/pyiriplas/kp1957
RMextract/pyiriplas/kp1951
RMextract/pyiriplas/kp1975
RMextract/pyiriplas/kp1950
RMextract/pyiriplas/kp2013
RMextract/pyiriplas/kp2010
RMextract/pyiriplas/kp1967
RMextract/pyiriplas/apf107.dat
RMextract/pyiriplas/kp2001
RMextract/pyiriplas/kp1959
RMextract/pyiriplas/kp2020.txt
RMextract/pyiriplas/ursi11.ASC
RMextract/pyiriplas/dgrf2010.dat
RMextract/pyiriplas/kp1965
RMextract/pyiriplas/igrf2020.dat
RMextract/pyiriplas/ccir21.asc
RMextract/pyiriplas/kp2014
RMextract/pyiriplas/kp1963
