Metadata-Version: 2.1
Name: RMextract
Version: 0.5.1
Summary: Extract TEC, vTEC, Earthmagnetic field and Rotation Measures from GPS and WMM data for radio interferometry observations 
Author-email: Maaijke Mevius <mevius@astron.nl>
Maintainer-email: Marcel Loose <loose@astron.nl>
License: GNU GENERAL PUBLIC LICENSE
Project-URL: Source, https://github.com/lofar-astron/RMextract
Classifier: Development Status :: 4 - Beta
Classifier: Intended Audience :: Science/Research
Classifier: License :: OSI Approved :: GNU General Public License v3 (GPLv3)
Classifier: Operating System :: POSIX :: Linux
Classifier: Programming Language :: Python
Classifier: Topic :: Scientific/Engineering :: Astronomy
Classifier: Topic :: Software Development :: Libraries :: Python Modules
Requires-Python: >=3.7
License-File: LICENSE
Requires-Dist: astropy
Requires-Dist: numpy
Requires-Dist: PySocks
Requires-Dist: scipy
Requires-Dist: importlib-resources; python_version < "3.9"
Provides-Extra: lofar-utils
Requires-Dist: losoto; extra == "lofar-utils"
Requires-Dist: python-casacore; extra == "lofar-utils"
